jeejuh_dl/__init__.py
jeejuh_dl/__main__.py
jeejuh_dl/main.py
jeejuh_dl-1.1.dist-info/entry_points.txt
jeejuh_dl-1.1.dist-info/WHEEL
jeejuh_dl-1.1.dist-info/METADATA
jeejuh_dl-1.1.dist-info/RECORD
