Metadata-Version: 2.1
Name: jeejuh-dl
Version: 1.1
Summary: Downloads links from jeejuh.com purchases
Home-page: https://github.com/daddycocoaman/JeeJuh-Downloader
License: MIT
Author: Leron Gray
Requires-Python: >=3.8,<4.0
Classifier: License :: OSI Approved :: MIT License
Classifier: Programming Language :: Python :: 3
Classifier: Programming Language :: Python :: 3.8
Classifier: Programming Language :: Python :: 3.9
Requires-Dist: gazpacho (>=1.1,<2.0)
Requires-Dist: rich (>=9.8.2,<10.0.0)
Requires-Dist: typer (>=0.3.2,<0.4.0)
